MANIFEST.in
setup.py
cmd/upython
upython/__init__.py
upython/pyboard.py
upython/snippets.py
upython/upython.py
upython.egg-info/PKG-INFO
upython.egg-info/SOURCES.txt
upython.egg-info/dependency_links.txt
upython.egg-info/requires.txt
upython.egg-info/top_level.txt