Metadata-Version: 1.2
Name: upython
Version: 0.2
Summary: MicroPython
Home-page: UNKNOWN
Author: Yeison Cardona
Author-email: yeisoneng@gmail.com
Maintainer: Yeison Cardona
Maintainer-email: yeisoneng@gmail.com
License: BSD License
Download-URL: https://bitbucket.org/yeisoneng/upython/downloads/
Platform: UNKNOWN
